{
    "configurations": [
        {
            "browse": {
                "databaseFilename": "${default}",
                "limitSymbolsToIncludedHeaders": false
            },
            "includePath": [
                "/home/ekyriakos/my_ws/install/turtle_interfaces/include/**",
                "/opt/ros/galactic/include/**",
                "/usr/include/**",
                "/home/ekyriakos/my_ws/src/turtle_doctor_cpp/include/**"
            ],
            "name": "ROS",
            "intelliSenseMode": "gcc-x64",
            "compilerPath": "/usr/bin/gcc",
            "cStandard": "gnu11",
            "cppStandard": "c++14"
        }
    ],
    "version": 4
}